MANIFEST.in
README.rst
requirements.txt
setup.cfg
setup.py
moogli/__init__.py
moogli.egg-info/PKG-INFO
moogli.egg-info/SOURCES.txt
moogli.egg-info/dependency_links.txt
moogli.egg-info/top_level.txt
moogli/include/core/Compartment.hpp
moogli/include/core/Network.hpp
moogli/include/core/Neuron.hpp
moogli/include/core/Voxel.hpp
moogli/include/mesh/CylinderMesh.hpp
moogli/include/mesh/SphereMesh.hpp
moogli/include/utility/constants.hpp
moogli/include/utility/conversions.hpp
moogli/include/utility/globals.hpp
moogli/include/utility/libraries.hpp
moogli/include/utility/record.hpp
moogli/include/view/NetworkViewer.hpp
moogli/moc/NetworkViewer.moc.cpp
moogli/reader/__init__.py
moogli/simulator/__init__.py
moogli/simulator/moose.py
moogli/sip/moogli.sip
moogli/src/core/Compartment.cpp
moogli/src/core/Network.cpp
moogli/src/core/Neuron.cpp
moogli/src/core/Voxel.cpp
moogli/src/mesh/CylinderMesh.cpp
moogli/src/mesh/SphereMesh.cpp
moogli/src/utility/conversions.cpp
moogli/src/utility/globals.cpp
moogli/src/utility/record.cpp
moogli/src/view/NetworkViewer.cpp
scripts/moogli_color_update.py
scripts/moogli_purkinje_simulation.py
scripts/moogli_purkinje_simulation_with_rm.py
scripts/moogli_purkinje_simulation_with_rm_and_graph.py
scripts/moogli_simple_viewing.py